noachuartzt_sales/sales.py
noachuartzt_sales/settings.py
noachuartzt_sales-0.0.1.dist-info/METADATA
noachuartzt_sales-0.0.1.dist-info/WHEEL
noachuartzt_sales-0.0.1.dist-info/RECORD
