Metadata-Version: 2.1
Name: noachuartzt_sales
Version: 0.0.1
Summary: My customized ORM on Sales
Project-URL: Homepage, https://github.com/noachuartzt/sales
Project-URL: Bug Tracker, https://github.com/noachuartzt/sales/issues
Author-email: noachuartzt <noa.chu.artzt@alumnos.upm.es>
Classifier: License :: OSI Approved :: MIT License
Classifier: Operating System :: OS Independent
Classifier: Programming Language :: Python :: 3
Requires-Python: >=3.9
